{
  "timestamp": "2025-12-31T14:23:55.504350",
  "summary": {
    "total_articles": 25,
    "avg_relevance": 7.0,
    "bullish": 11,
    "neutral": 10,
    "bearish": 4,
    "high_priority": 8,
    "material_events": 4
  },
  "sources": {
    "Bank Indonesia": 1,
    "Indonesia Stock Exchange": 1,
    "BPS Statistics Indonesia": 1,
    "Federal Reserve": 1,
    "Reuters": 3,
    "Bloomberg": 2,
    "Caixin/S&P Global": 1,
    "MarketWatch": 2,
    "CNBC": 11,
    "TradingNEWS": 1,
    "The Wall Street Journal": 1
  },
  "top_signals": [
    {
      "headline": "Bank Indonesia Holds BI-Rate at 5.75% to Support Rupiah Stability",
      "score": 9,
      "source": "Bank Indonesia",
      "sentiment": "neutral",
      "impact": "The central bank maintained its benchmark rate amid global uncertainty, balancing growth support with currency stability. Foreign reserves remain robust at $151.8B, providing FX intervention capacity.",
      "category": "indonesia_monetary_policy",
      "date": "2025-12-31 14:23",
      "link": "https://www.bi.go.id/en/publikasi/ruang-media/news-release/default.aspx"
    },
    {
      "headline": "JCI Index Resilient Above 7,200 as Foreign Flows Turn Positive",
      "score": 9,
      "source": "Indonesia Stock Exchange",
      "sentiment": "positive",
      "impact": "Jakarta Composite Index maintains strength driven by banking and consumer sectors. Net foreign buying resumed as EM sentiment improves on Fed pivot expectations. YTD performance +2.3%.",
      "category": "indonesia_equities",
      "date": "2025-12-31 14:23",
      "link": "https://www.idx.co.id/en/market-data/statistical-data/composite-index/"
    },
    {
      "headline": "Indonesia Q3 GDP Grows 5.12% YoY, Beats Consensus Estimates",
      "score": 9,
      "source": "BPS Statistics Indonesia",
      "sentiment": "positive",
      "impact": "Economic expansion driven by household consumption (+4.9%) and fixed investment (+5.1%). Manufacturing PMI at 52.3 signals continued expansion. Full-year growth projected at 5.05-5.15%.",
      "category": "indonesia_economy",
      "date": "2025-12-31 14:23",
      "link": "https://www.bps.go.id/en/statistics-table/2/MTk3NSMy/gross-domestic-product--gdp-.html"
    },
    {
      "headline": "Federal Reserve Signals Potential December Rate Cut Amid Cooling Inflation",
      "score": 9,
      "source": "Federal Reserve",
      "sentiment": "positive",
      "impact": "FOMC minutes suggest committee members see conditions for further easing. Core PCE trending toward 2.5% target. Markets pricing 65% probability of 25bp cut in December.",
      "category": "us_monetary_policy",
      "date": "2025-12-31 14:23",
      "link": "https://www.federalreserve.gov/monetarypolicy.htm"
    },
    {
      "headline": "Indonesian Rupiah Stabilizes at 15,850/USD on Trade Surplus",
      "score": 8,
      "source": "Reuters",
      "sentiment": "neutral",
      "impact": "Currency finds support from continued trade surplus ($10.5B Q3) and BI intervention. Carry trade dynamics remain favorable vs USD. Key resistance at 16,000 level.",
      "category": "indonesia_fx",
      "date": "2025-12-31 14:23",
      "link": "https://www.reuters.com/markets/currencies/"
    },
    {
      "headline": "Indonesian Banks Report Strong NIM Expansion in Q3 Results",
      "score": 8,
      "source": "Bloomberg",
      "sentiment": "positive",
      "impact": "Major banks (BBCA, BBRI, BMRI) posted 12-15% earnings growth with NIMs expanding to 5.2-5.8%. Loan growth accelerated to 11.5% YoY. NPL ratios stable at 2.1-2.4%.",
      "category": "indonesia_financials",
      "date": "2025-12-31 14:23",
      "link": "https://www.bloomberg.com/asia"
    },
    {
      "headline": "S&P 500 Approaches All-Time High on AI Optimism and Rate Cut Bets",
      "score": 8,
      "source": "Bloomberg",
      "sentiment": "positive",
      "impact": "Index trading near 6,000 level as tech sector leads. Magnificent 7 stocks contribute 60% of YTD gains. Earnings growth re-accelerating to +8% YoY in Q4.",
      "category": "us_equities",
      "date": "2025-12-31 14:23",
      "link": "https://www.bloomberg.com/markets"
    },
    {
      "headline": "US 10-Year Treasury Yield Falls to 4.35% on Dovish Fed Outlook",
      "score": 8,
      "source": "Reuters",
      "sentiment": "neutral",
      "impact": "Bond yields decline as markets reprice Fed trajectory. Real yields at +2.0% remain attractive for fixed income allocations. Duration positioning shifts to neutral.",
      "category": "fixed_income",
      "date": "2025-12-31 14:23",
      "link": "https://www.reuters.com/markets/rates-bonds/"
    },
    {
      "headline": "China Manufacturing PMI Expands to 51.5, Supporting EM Sentiment",
      "score": 7,
      "source": "Caixin/S&P Global",
      "sentiment": "positive",
      "impact": "Factory activity strengthens on stimulus measures and export recovery. Positive read-through for Asian supply chains and commodity demand. EM currencies rally.",
      "category": "asia_economy",
      "date": "2025-12-31 14:23",
      "link": "https://www.pmi.spglobal.com/Public/Home/PressRelease/"
    },
    {
      "headline": "Brent Crude Holds at $78/bbl as OPEC+ Maintains Production Discipline",
      "score": 7,
      "source": "Reuters",
      "sentiment": "neutral",
      "impact": "Oil prices stabilize on balanced supply-demand outlook. OPEC+ compliance remains high at 95%. Inventory levels normalize. Range-bound trading expected near term.",
      "category": "commodities",
      "date": "2025-12-31 14:23",
      "link": "https://www.reuters.com/business/energy/"
    },
    {
      "headline": "Interest rates could be on hold \u2018for some time,\u2019 Fed minutes show",
      "score": 7,
      "source": "MarketWatch",
      "sentiment": "negative",
      "impact": "A pause would give Fed time to assess the effects of the three rate cuts made this year.",
      "category": "us_monetary_policy",
      "date": "2025-12-30 19:13",
      "link": "https://www.marketwatch.com/story/interest-rates-could-be-on-hold-for-some-time-fed-minutes-show-f799db89"
    },
    {
      "headline": "Stocks are little changed after S&P 500 posts back-to-back losses: Live updates",
      "score": 7,
      "source": "CNBC",
      "sentiment": "negative",
      "impact": "Stocks slipped on Monday as investors sold their tech holdings heading into the end of 2025.",
      "category": "us_equities",
      "date": "2025-12-30 14:32",
      "link": "https://www.cnbc.com/2025/12/29/stock-market-today-live-updates.html"
    },
    {
      "headline": "Nike shares move higher on big insider purchases by CEO Elliott Hill, director Tim Cook after down year",
      "score": 6,
      "source": "CNBC",
      "sentiment": "positive",
      "impact": "The retailer's insiders picked up shares near the end of a rough year.",
      "category": "us_equities",
      "date": "2025-12-31 13:58",
      "link": "https://www.cnbc.com/2025/12/31/nike-shares-insider-buying-tim-cook.html"
    },
    {
      "headline": "SPYD ETF Price at $43.57: Is This High-Dividend S&P 500 Fund Still Cheap for 2026?",
      "score": 6,
      "source": "TradingNEWS",
      "sentiment": "positive",
      "impact": "The article discusses the SPYD ETF at its current price of $43.57, evaluating its potential as a high-dividend S&P 500 fund into 2026. It analyzes the macro and equity market backdrops, including Fed rate cuts, inflation, and the S&P 500's performance, to determine if SPYD remains an attractive inve",
      "category": "us_equities",
      "date": "2025-12-31 13:09",
      "link": "https://www.tradingnews.com/news/spyd-etf-price-at-43-usd-high-dividend-sp-500-fund"
    },
    {
      "headline": "\u2018I\u2019m fed up\u2019: My selfish mother-in-law has controlled me for 30 years. How can I regain my power?",
      "score": 6,
      "source": "MarketWatch",
      "sentiment": "positive",
      "impact": "\u201cI\u2019m almost 50 years old. Enough is enough. I am exhausted by it.\u201d",
      "category": "us_monetary_policy",
      "date": "2025-12-31 13:00",
      "link": "https://www.marketwatch.com/story/im-completely-fed-up-my-selfish-boomer-mother-in-law-has-controlled-me-for-30-years-how-can-i-regain-my-power-7d6b82e0?mod=mw_rss_topstories"
    },
    {
      "headline": "Tech startup Hyphen is bringing AI to the lunch line \u2014 with help from Cava and Chipotle",
      "score": 6,
      "source": "CNBC",
      "sentiment": "neutral",
      "impact": "Hyphen aims to make service better and more efficient, and it has investors including Cava and Chipotle.",
      "category": "global_markets",
      "date": "2025-12-30 18:42",
      "link": "https://www.cnbc.com/2025/12/30/hyphen-automated-makelines-investments-cava-chipotle.html"
    },
    {
      "headline": "Home prices are getting slightly more affordable, but down payments are still holding buyers back",
      "score": 6,
      "source": "CNBC",
      "sentiment": "negative",
      "impact": "Housing is getting more affordable thanks to lower prices and lower mortgage rates, but it still takes more time to save for a down payment than pre-pandemic.",
      "category": "us_equities",
      "date": "2025-12-30 17:56",
      "link": "https://www.cnbc.com/2025/12/30/home-prices-affordable-down-payments-buyers.html"
    },
    {
      "headline": "These restaurant chains closed locations in 2025",
      "score": 6,
      "source": "CNBC",
      "sentiment": "negative",
      "impact": "Chains like Starbucks, Wendy's and Denny's announced plans to close underperforming restaurants in 2025.",
      "category": "global_markets",
      "date": "2025-12-30 17:10",
      "link": "https://www.cnbc.com/2025/12/30/2025-restaurant-closures-starbucks-wendys.html"
    },
    {
      "headline": "33-year-old left fine dining to become a private chef. Now she works up to 25 hours a week and makes 'the same income'\u2014'I really enjoy the freedom'",
      "score": 6,
      "source": "CNBC",
      "sentiment": "neutral",
      "impact": "Cintia Diaz, 33, left fine dining to become a private chef in New York City. She says it's helped her work-life balance, as she works 20 to 25 hours a week now.",
      "category": "global_markets",
      "date": "2025-12-30 16:10",
      "link": "https://www.cnbc.com/2025/12/30/33-year-old-left-the-restaurant-business-to-become-a-private-chef.html"
    },
    {
      "headline": "Here\u2019s what to expect for commercial real estate in 2026",
      "score": 6,
      "source": "CNBC",
      "sentiment": "positive",
      "impact": "Experts and research firms forecast a year of stabilization and recovery for commercial real estate in 2026. ",
      "category": "global_markets",
      "date": "2025-12-30 15:15",
      "link": "https://www.cnbc.com/2025/12/30/commercial-real-estate-2026-what-to-expect.html"
    },
    {
      "headline": "Your work calendar is a mess. Use these expert tips to declutter and free up time heading into 2026.",
      "score": 6,
      "source": "CNBC",
      "sentiment": "neutral",
      "impact": "Experts shared tips for cleaning up and better managing your work calendar in 2026.",
      "category": "global_markets",
      "date": "2025-12-30 15:05",
      "link": "https://www.cnbc.com/2025/12/30/how-to-make-your-work-calendar-feel-less-overwhelming-in-2026.html"
    },
    {
      "headline": "If you want people to say 'yes' to you more often, use these 4 easy phrases: Psychology expert",
      "score": 6,
      "source": "CNBC",
      "sentiment": "neutral",
      "impact": "If you want to be more persuasive in both work and life, psychology expert Shad\u00e9 Zahrai shares her most \"counterintuitive\" advice for getting people to say \"yes.\"",
      "category": "global_markets",
      "date": "2025-12-30 14:30",
      "link": "https://www.cnbc.com/2025/12/30/psychology-expert-4-phrases-that-will-get-people-to-say-yes-to-you-more-often.html"
    },
    {
      "headline": "The Club's top 10 things to watch in the stock market Tuesday",
      "score": 6,
      "source": "CNBC",
      "sentiment": "neutral",
      "impact": "Copper is on track for its biggest one-year increase since 2009. Meanwhile, Meta announced one last acquisition of 2025.",
      "category": "global_markets",
      "date": "2025-12-30 14:11",
      "link": "https://www.cnbc.com/2025/12/30/the-clubs-top-10-things-to-watch-in-the-stock-market-tuesday.html"
    },
    {
      "headline": "'We're pretty upbeat': Stock market experts expect continued growth, bolstered by AI, in 2026",
      "score": 6,
      "source": "CNBC",
      "sentiment": "positive",
      "impact": "Wall Street analysts expect growth in both the economy and corporate earnings next year, both of which bode well for stocks.",
      "category": "global_markets",
      "date": "2025-12-30 14:00",
      "link": "https://www.cnbc.com/2025/12/30/were-pretty-upbeat-stock-market-experts-expect-continued-growth-bolstered-by-ai-in-2026.html"
    },
    {
      "headline": "Be Prepared to Keep Paying More for Electricity",
      "score": 6,
      "source": "The Wall Street Journal",
      "sentiment": "neutral",
      "impact": "Data centers are getting much of the blame lately for rising power costs, but they aren\u2019t the only catalyst",
      "category": "us_equities",
      "date": "2025-12-30 10:37",
      "link": "https://www.wsj.com/business/energy-oil/be-prepared-to-keep-paying-more-for-electricity-31462755"
    }
  ]
}